scooter/__init__.py
scooter/__main__.py
scooter/import_.py
scooter/database/__init__.py
scooter/database/storage.py
scooter/infrastructure/__init__.py
scooter/infrastructure/numbers.py
scooter/infrastructure/switch.py
scooter/models/__init__.py
scooter/models/__models.py
scooter/models/locations.py
scooter/models/rentals.py
scooter/models/scooters.py
scooter/models/sessions.py
scooter/models/users.py
scooter/services/__init__.py
scooter/services/service.py
scooter_rental-0.0.3.dist-info/AUTHORS.md
scooter_rental-0.0.3.dist-info/LICENSE.md
scooter_rental-0.0.3.dist-info/METADATA
scooter_rental-0.0.3.dist-info/WHEEL
scooter_rental-0.0.3.dist-info/entry_points.txt
scooter_rental-0.0.3.dist-info/top_level.txt
scooter_rental-0.0.3.dist-info/RECORD
