Metadata-Version: 2.1
Name: scooter-rental
Version: 0.0.3
Summary: A command line application for renting electro-scooters. Just try it, it is fun :)
Home-page: https://github.com/vyahello/rent-electro-scooter
Author: Volodymyr Yahello
Author-email: vyahello@gmail.com
License: UNKNOWN
Platform: UNKNOWN
Classifier: Programming Language :: Python :: 3.6
Classifier: Programming Language :: Python :: 3.7
Classifier: Programming Language :: Python :: 3.8
Classifier: License :: OSI Approved :: GNU General Public License v3 (GPLv3)
Classifier: Operating System :: OS Independent
Requires-Python: >=3.6
Requires-Dist: sqlalchemy (==1.3.13)
Requires-Dist: alembic (==1.4.2)
